tmq
tmq_cuda
tmq_native
