Metadata-Version: 2.1
Name: tmq
Version: 0.1.2
Summary: Quantization-aware neural network layers using controllable soft-quantization
Author: Martin Wawro
Author-email: Martin Wawro <martin.wawro@gmail.com>
License: Mozilla Public License Version 2.0
Project-URL: Homepage, https://github.com/mtnwrw/tmq
Project-URL: Bug Tracker, https://github.com/mtnwrw/tmq/issues
Requires-Python: >=3.8
License-File: LICENSE
